pyspark_factories/__init__.py
pyspark_factories/factory.py
pyspark_factories/fields.py
pyspark_factories/handlers/decimal.py
pyspark_factories/value_generators/primitives.py
pyspark_factories-0.0.1.dist-info/METADATA
pyspark_factories-0.0.1.dist-info/WHEEL
pyspark_factories-0.0.1.dist-info/RECORD
