Metadata-Version: 2.1
Name: pyspark-factories
Version: 0.0.1
Summary: Create pyspark dataframes with randomly generated data from structschema
Author: Daan Rademaker
Author-email: d.v.rademaker@gmail.com
Requires-Python: >=3.7,<4.0
Classifier: Programming Language :: Python :: 3
Classifier: Programming Language :: Python :: 3.7
Classifier: Programming Language :: Python :: 3.8
Classifier: Programming Language :: Python :: 3.9
Classifier: Programming Language :: Python :: 3.10
Classifier: Programming Language :: Python :: 3.11
Requires-Dist: Faker (>=13.3.1,<14.0.0)
Requires-Dist: dotmap (>=1.3.30,<2.0.0)
Requires-Dist: pyspark (>=3.2.1,<4.0.0)
